{
  "instructors": [
    {
      "id": "703c",
      "fullName": "karna",
      "contactNumber": "08868817364",
      "email": "shekharjugtwan2002@gmail.com",
      "experience": 1,
      "teachingDomain": "Mathematics",
      "specialization": "Programming",
      "degree": "dfa",
      "certifications": "adsfadsf",
      "daysAvailable": "",
      "hoursAvailable": "",
      "resume": null
    },
    {
      "id": "e29d",
      "fullName": "shyam",
      "contactNumber": "08868817364",
      "email": "shekharjugtwan2002@gmail.com",
      "experience": 2,
      "teachingDomain": "Computer Science",
      "specialization": "Data Structures",
      "degree": "M Tech - CSE",
      "certifications": " SAP cloud computing",
      "daysAvailable": "45",
      "hoursAvailable": "1024",
      "resume": null
    },
    {
      "id": "ef31",
      "fullName": "",
      "contactNumber": "",
      "email": "",
      "experience": "",
      "teachingDomain": "",
      "specialization": "",
      "degree": "",
      "certifications": "",
      "daysAvailable": "",
      "hoursAvailable": "",
      "resume": null
    }
  ],
  "shorlistedInstructors": [
    {
      "id": "703c",
      "fullName": "karna",
      "contactNumber": "08868817364",
      "email": "shekharjugtwan2002@gmail.com",
      "experience": 1,
      "teachingDomain": "Mathematics",
      "specialization": "Programming",
      "degree": "dfa",
      "certifications": "adsfadsf",
      "daysAvailable": "",
      "hoursAvailable": "",
      "resume": null
    },
    {
      "id": "2a4c",
      "fullName": "ram",
      "contactNumber": "08868817364",
      "email": "shekharjugtwan2002@gmail.com",
      "experience": 1,
      "teachingDomain": "Mathematics",
      "specialization": "Programming",
      "degree": "bgfaedfa",
      "certifications": "adsfadsf",
      "daysAvailable": "45",
      "hoursAvailable": "46",
      "resume": "C:\\fakepath\\shekhar resume 2.0.pdf"
    },
    {
      "id": "e29d",
      "fullName": "shyam",
      "contactNumber": "08868817364",
      "email": "shekharjugtwan2002@gmail.com",
      "experience": 2,
      "teachingDomain": "Computer Science",
      "specialization": "Data Structures",
      "degree": "M Tech - CSE",
      "certifications": " SAP cloud computing",
      "daysAvailable": "45",
      "hoursAvailable": "1024",
      "resume": null
    },
    {
      "id": "ef31",
      "fullName": "",
      "contactNumber": "",
      "email": "",
      "experience": "",
      "teachingDomain": "",
      "specialization": "",
      "degree": "",
      "certifications": "",
      "daysAvailable": "",
      "hoursAvailable": "",
      "resume": null
    }
  ]
}